{
  "surahNumber": 81,
  "surahName": "At-Takwir",
  "surahNameArabic": "التكوير",
  "lastUpdated": "2026-02-02T05:39:52.007Z",
  "vocabularyQuiz": [
    {
      "id": "vocab_81_1",
      "arabicWord": "إِذَا",
      "normalizedForm": "إذا",
      "transliteration": "",
      "correctMeaning": "",
      "distractors": [],
      "translationStatus": "pending",
      "matchType": null,
      "ayahReference": "81:1",
      "occurrenceCount": 3,
      "allOccurrences": [
        {
          "ayahRef": "81:1",
          "position": 0
        },
        {
          "ayahRef": "81:17",
          "position": 1
        },
        {
          "ayahRef": "81:18",
          "position": 1
        }
      ],
      "difficulty": "medium",
      "category": "unknown",
      "tags": [
        "needs-review"
      ]
    },
    {
      "id": "vocab_81_2",
      "arabicWord": "ٱلشَّمۡسُ",
      "normalizedForm": "الشمس",
      "transliteration": "Shams",
      "correctMeaning": "Sun",
      "distractors": [
        "The book",
        "The path",
        "The day"
      ],
      "translationStatus": "complete",
      "matchType": "root",
      "ayahReference": "81:1",
      "occurrenceCount": 1,
      "allOccurrences": [
        {
          "ayahRef": "81:1",
          "position": 1
        }
      ],
      "difficulty": "hard",
      "category": "noun",
      "tags": [
        "noun"
      ]
    },
    {
      "id": "vocab_81_3",
      "arabicWord": "كُوِّرَتۡ",
      "normalizedForm": "كورت",
      "transliteration": "",
      "correctMeaning": "",
      "distractors": [],
      "translationStatus": "pending",
      "matchType": null,
      "ayahReference": "81:1",
      "occurrenceCount": 1,
      "allOccurrences": [
        {
          "ayahRef": "81:1",
          "position": 2
        }
      ],
      "difficulty": "hard",
      "category": "unknown",
      "tags": [
        "needs-review"
      ]
    },
    {
      "id": "vocab_81_4",
      "arabicWord": "وَإِذَا",
      "normalizedForm": "وإذا",
      "transliteration": "",
      "correctMeaning": "",
      "distractors": [],
      "translationStatus": "pending",
      "matchType": null,
      "ayahReference": "81:2",
      "occurrenceCount": 11,
      "allOccurrences": [
        {
          "ayahRef": "81:2",
          "position": 0
        },
        {
          "ayahRef": "81:3",
          "position": 0
        },
        {
          "ayahRef": "81:4",
          "position": 0
        },
        {
          "ayahRef": "81:5",
          "position": 0
        },
        {
          "ayahRef": "81:6",
          "position": 0
        },
        {
          "ayahRef": "81:7",
          "position": 0
        },
        {
          "ayahRef": "81:8",
          "position": 0
        },
        {
          "ayahRef": "81:10",
          "position": 0
        },
        {
          "ayahRef": "81:11",
          "position": 0
        },
        {
          "ayahRef": "81:12",
          "position": 0
        },
        {
          "ayahRef": "81:13",
          "position": 0
        }
      ],
      "difficulty": "easy",
      "category": "unknown",
      "tags": [
        "needs-review"
      ]
    },
    {
      "id": "vocab_81_5",
      "arabicWord": "ٱلنُّجُومُ",
      "normalizedForm": "النجوم",
      "transliteration": "Lan",
      "correctMeaning": "Will not",
      "distractors": [
        "Not",
        "Indeed",
        "When"
      ],
      "translationStatus": "complete",
      "matchType": "partial",
      "ayahReference": "81:2",
      "occurrenceCount": 1,
      "allOccurrences": [
        {
          "ayahRef": "81:2",
          "position": 1
        }
      ],
      "difficulty": "hard",
      "category": "particle",
      "tags": [
        "particle"
      ]
    },
    {
      "id": "vocab_81_6",
      "arabicWord": "ٱنكَدَرَتۡ",
      "normalizedForm": "انكدرت",
      "transliteration": "Anna/Inna",
      "correctMeaning": "That/Indeed",
      "distractors": [
        "Not",
        "Indeed",
        "When"
      ],
      "translationStatus": "complete",
      "matchType": "partial",
      "ayahReference": "81:2",
      "occurrenceCount": 1,
      "allOccurrences": [
        {
          "ayahRef": "81:2",
          "position": 2
        }
      ],
      "difficulty": "hard",
      "category": "particle",
      "tags": [
        "particle"
      ]
    },
    {
      "id": "vocab_81_7",
      "arabicWord": "ٱلۡجِبَالُ",
      "normalizedForm": "الجبال",
      "transliteration": "",
      "correctMeaning": "",
      "distractors": [],
      "translationStatus": "pending",
      "matchType": null,
      "ayahReference": "81:3",
      "occurrenceCount": 1,
      "allOccurrences": [
        {
          "ayahRef": "81:3",
          "position": 1
        }
      ],
      "difficulty": "hard",
      "category": "unknown",
      "tags": [
        "needs-review"
      ]
    },
    {
      "id": "vocab_81_8",
      "arabicWord": "سُيِّرَتۡ",
      "normalizedForm": "سيرت",
      "transliteration": "",
      "correctMeaning": "",
      "distractors": [],
      "translationStatus": "pending",
      "matchType": null,
      "ayahReference": "81:3",
      "occurrenceCount": 1,
      "allOccurrences": [
        {
          "ayahRef": "81:3",
          "position": 2
        }
      ],
      "difficulty": "hard",
      "category": "unknown",
      "tags": [
        "needs-review"
      ]
    },
    {
      "id": "vocab_81_9",
      "arabicWord": "ٱلۡعِشَارُ",
      "normalizedForm": "العشار",
      "transliteration": "",
      "correctMeaning": "",
      "distractors": [],
      "translationStatus": "pending",
      "matchType": null,
      "ayahReference": "81:4",
      "occurrenceCount": 1,
      "allOccurrences": [
        {
          "ayahRef": "81:4",
          "position": 1
        }
      ],
      "difficulty": "hard",
      "category": "unknown",
      "tags": [
        "needs-review"
      ]
    },
    {
      "id": "vocab_81_10",
      "arabicWord": "عُطِّلَتۡ",
      "normalizedForm": "عطلت",
      "transliteration": "",
      "correctMeaning": "",
      "distractors": [],
      "translationStatus": "pending",
      "matchType": null,
      "ayahReference": "81:4",
      "occurrenceCount": 1,
      "allOccurrences": [
        {
          "ayahRef": "81:4",
          "position": 2
        }
      ],
      "difficulty": "hard",
      "category": "unknown",
      "tags": [
        "needs-review"
      ]
    },
    {
      "id": "vocab_81_11",
      "arabicWord": "ٱلۡوُحُوشُ",
      "normalizedForm": "الوحوش",
      "transliteration": "Law",
      "correctMeaning": "If",
      "distractors": [
        "Not",
        "Indeed",
        "When"
      ],
      "translationStatus": "complete",
      "matchType": "partial",
      "ayahReference": "81:5",
      "occurrenceCount": 1,
      "allOccurrences": [
        {
          "ayahRef": "81:5",
          "position": 1
        }
      ],
      "difficulty": "hard",
      "category": "particle",
      "tags": [
        "particle"
      ]
    },
    {
      "id": "vocab_81_12",
      "arabicWord": "حُشِرَتۡ",
      "normalizedForm": "حشرت",
      "transliteration": "Sharr",
      "correctMeaning": "Evil",
      "distractors": [
        "The book",
        "The path",
        "The day"
      ],
      "translationStatus": "complete",
      "matchType": "partial",
      "ayahReference": "81:5",
      "occurrenceCount": 1,
      "allOccurrences": [
        {
          "ayahRef": "81:5",
          "position": 2
        }
      ],
      "difficulty": "hard",
      "category": "noun",
      "tags": [
        "noun"
      ]
    },
    {
      "id": "vocab_81_13",
      "arabicWord": "ٱلۡبِحَارُ",
      "normalizedForm": "البحار",
      "transliteration": "",
      "correctMeaning": "",
      "distractors": [],
      "translationStatus": "pending",
      "matchType": null,
      "ayahReference": "81:6",
      "occurrenceCount": 1,
      "allOccurrences": [
        {
          "ayahRef": "81:6",
          "position": 1
        }
      ],
      "difficulty": "hard",
      "category": "unknown",
      "tags": [
        "needs-review"
      ]
    },
    {
      "id": "vocab_81_14",
      "arabicWord": "سُجِّرَتۡ",
      "normalizedForm": "سجرت",
      "transliteration": "",
      "correctMeaning": "",
      "distractors": [],
      "translationStatus": "pending",
      "matchType": null,
      "ayahReference": "81:6",
      "occurrenceCount": 1,
      "allOccurrences": [
        {
          "ayahRef": "81:6",
          "position": 2
        }
      ],
      "difficulty": "hard",
      "category": "unknown",
      "tags": [
        "needs-review"
      ]
    },
    {
      "id": "vocab_81_15",
      "arabicWord": "ٱلنُّفُوسُ",
      "normalizedForm": "النفوس",
      "transliteration": "Lan",
      "correctMeaning": "Will not",
      "distractors": [
        "Not",
        "Indeed",
        "When"
      ],
      "translationStatus": "complete",
      "matchType": "partial",
      "ayahReference": "81:7",
      "occurrenceCount": 1,
      "allOccurrences": [
        {
          "ayahRef": "81:7",
          "position": 1
        }
      ],
      "difficulty": "hard",
      "category": "particle",
      "tags": [
        "particle"
      ]
    },
    {
      "id": "vocab_81_16",
      "arabicWord": "زُوِّجَتۡ",
      "normalizedForm": "زوجت",
      "transliteration": "Zawj",
      "correctMeaning": "Spouse",
      "distractors": [
        "The book",
        "The path",
        "The day"
      ],
      "translationStatus": "complete",
      "matchType": "partial",
      "ayahReference": "81:7",
      "occurrenceCount": 1,
      "allOccurrences": [
        {
          "ayahRef": "81:7",
          "position": 2
        }
      ],
      "difficulty": "hard",
      "category": "noun",
      "tags": [
        "noun"
      ]
    },
    {
      "id": "vocab_81_17",
      "arabicWord": "ٱلۡمَوۡءُۥدَةُ",
      "normalizedForm": "الموءدة",
      "transliteration": "Lam",
      "correctMeaning": "Did not",
      "distractors": [
        "Not",
        "Indeed",
        "When"
      ],
      "translationStatus": "complete",
      "matchType": "partial",
      "ayahReference": "81:8",
      "occurrenceCount": 1,
      "allOccurrences": [
        {
          "ayahRef": "81:8",
          "position": 1
        }
      ],
      "difficulty": "hard",
      "category": "particle",
      "tags": [
        "particle"
      ]
    },
    {
      "id": "vocab_81_18",
      "arabicWord": "سُئِلَتۡ",
      "normalizedForm": "سئلت",
      "transliteration": "",
      "correctMeaning": "",
      "distractors": [],
      "translationStatus": "pending",
      "matchType": null,
      "ayahReference": "81:8",
      "occurrenceCount": 1,
      "allOccurrences": [
        {
          "ayahRef": "81:8",
          "position": 2
        }
      ],
      "difficulty": "hard",
      "category": "unknown",
      "tags": [
        "needs-review"
      ]
    },
    {
      "id": "vocab_81_19",
      "arabicWord": "بِأَيِّ",
      "normalizedForm": "بأي",
      "transliteration": "",
      "correctMeaning": "",
      "distractors": [],
      "translationStatus": "pending",
      "matchType": null,
      "ayahReference": "81:9",
      "occurrenceCount": 1,
      "allOccurrences": [
        {
          "ayahRef": "81:9",
          "position": 0
        }
      ],
      "difficulty": "hard",
      "category": "unknown",
      "tags": [
        "needs-review"
      ]
    },
    {
      "id": "vocab_81_20",
      "arabicWord": "ذَنۢبٖ",
      "normalizedForm": "ذنب",
      "transliteration": "Dhanb",
      "correctMeaning": "Sin",
      "distractors": [
        "The book",
        "The path",
        "The day"
      ],
      "translationStatus": "complete",
      "matchType": "exact",
      "ayahReference": "81:9",
      "occurrenceCount": 1,
      "allOccurrences": [
        {
          "ayahRef": "81:9",
          "position": 1
        }
      ],
      "difficulty": "hard",
      "category": "noun",
      "tags": [
        "noun"
      ]
    },
    {
      "id": "vocab_81_21",
      "arabicWord": "قُتِلَتۡ",
      "normalizedForm": "قتلت",
      "transliteration": "Qatala",
      "correctMeaning": "He killed",
      "distractors": [
        "He went",
        "They came",
        "We saw"
      ],
      "translationStatus": "complete",
      "matchType": "partial",
      "ayahReference": "81:9",
      "occurrenceCount": 1,
      "allOccurrences": [
        {
          "ayahRef": "81:9",
          "position": 2
        }
      ],
      "difficulty": "hard",
      "category": "verb",
      "tags": [
        "verb"
      ]
    },
    {
      "id": "vocab_81_22",
      "arabicWord": "ٱلصُّحُفُ",
      "normalizedForm": "الصحف",
      "transliteration": "",
      "correctMeaning": "",
      "distractors": [],
      "translationStatus": "pending",
      "matchType": null,
      "ayahReference": "81:10",
      "occurrenceCount": 1,
      "allOccurrences": [
        {
          "ayahRef": "81:10",
          "position": 1
        }
      ],
      "difficulty": "hard",
      "category": "unknown",
      "tags": [
        "needs-review"
      ]
    },
    {
      "id": "vocab_81_23",
      "arabicWord": "نُشِرَتۡ",
      "normalizedForm": "نشرت",
      "transliteration": "Sharr",
      "correctMeaning": "Evil",
      "distractors": [
        "The book",
        "The path",
        "The day"
      ],
      "translationStatus": "complete",
      "matchType": "partial",
      "ayahReference": "81:10",
      "occurrenceCount": 1,
      "allOccurrences": [
        {
          "ayahRef": "81:10",
          "position": 2
        }
      ],
      "difficulty": "hard",
      "category": "noun",
      "tags": [
        "noun"
      ]
    },
    {
      "id": "vocab_81_24",
      "arabicWord": "ٱلسَّمَآءُ",
      "normalizedForm": "السماء",
      "transliteration": "Sama",
      "correctMeaning": "Sky/Heaven",
      "distractors": [
        "The book",
        "The path",
        "The day"
      ],
      "translationStatus": "complete",
      "matchType": "root",
      "ayahReference": "81:11",
      "occurrenceCount": 1,
      "allOccurrences": [
        {
          "ayahRef": "81:11",
          "position": 1
        }
      ],
      "difficulty": "hard",
      "category": "noun",
      "tags": [
        "noun"
      ]
    },
    {
      "id": "vocab_81_25",
      "arabicWord": "كُشِطَتۡ",
      "normalizedForm": "كشطت",
      "transliteration": "",
      "correctMeaning": "",
      "distractors": [],
      "translationStatus": "pending",
      "matchType": null,
      "ayahReference": "81:11",
      "occurrenceCount": 1,
      "allOccurrences": [
        {
          "ayahRef": "81:11",
          "position": 2
        }
      ],
      "difficulty": "hard",
      "category": "unknown",
      "tags": [
        "needs-review"
      ]
    },
    {
      "id": "vocab_81_26",
      "arabicWord": "ٱلۡجَحِيمُ",
      "normalizedForm": "الجحيم",
      "transliteration": "",
      "correctMeaning": "",
      "distractors": [],
      "translationStatus": "pending",
      "matchType": null,
      "ayahReference": "81:12",
      "occurrenceCount": 1,
      "allOccurrences": [
        {
          "ayahRef": "81:12",
          "position": 1
        }
      ],
      "difficulty": "hard",
      "category": "unknown",
      "tags": [
        "needs-review"
      ]
    },
    {
      "id": "vocab_81_27",
      "arabicWord": "سُعِّرَتۡ",
      "normalizedForm": "سعرت",
      "transliteration": "",
      "correctMeaning": "",
      "distractors": [],
      "translationStatus": "pending",
      "matchType": null,
      "ayahReference": "81:12",
      "occurrenceCount": 1,
      "allOccurrences": [
        {
          "ayahRef": "81:12",
          "position": 2
        }
      ],
      "difficulty": "hard",
      "category": "unknown",
      "tags": [
        "needs-review"
      ]
    },
    {
      "id": "vocab_81_28",
      "arabicWord": "ٱلۡجَنَّةُ",
      "normalizedForm": "الجنة",
      "transliteration": "Jannah",
      "correctMeaning": "Paradise/Garden",
      "distractors": [
        "The book",
        "The path",
        "The day"
      ],
      "translationStatus": "complete",
      "matchType": "root",
      "ayahReference": "81:13",
      "occurrenceCount": 1,
      "allOccurrences": [
        {
          "ayahRef": "81:13",
          "position": 1
        }
      ],
      "difficulty": "hard",
      "category": "noun",
      "tags": [
        "noun"
      ]
    },
    {
      "id": "vocab_81_29",
      "arabicWord": "أُزۡلِفَتۡ",
      "normalizedForm": "أزلفت",
      "transliteration": "",
      "correctMeaning": "",
      "distractors": [],
      "translationStatus": "pending",
      "matchType": null,
      "ayahReference": "81:13",
      "occurrenceCount": 1,
      "allOccurrences": [
        {
          "ayahRef": "81:13",
          "position": 2
        }
      ],
      "difficulty": "hard",
      "category": "unknown",
      "tags": [
        "needs-review"
      ]
    },
    {
      "id": "vocab_81_30",
      "arabicWord": "عَلِمَتۡ",
      "normalizedForm": "علمت",
      "transliteration": "Lam",
      "correctMeaning": "Did not",
      "distractors": [
        "Not",
        "Indeed",
        "When"
      ],
      "translationStatus": "complete",
      "matchType": "partial",
      "ayahReference": "81:14",
      "occurrenceCount": 1,
      "allOccurrences": [
        {
          "ayahRef": "81:14",
          "position": 0
        }
      ],
      "difficulty": "hard",
      "category": "particle",
      "tags": [
        "particle"
      ]
    },
    {
      "id": "vocab_81_31",
      "arabicWord": "نَفۡسٞ",
      "normalizedForm": "نفس",
      "transliteration": "Nafs",
      "correctMeaning": "Soul/Self",
      "distractors": [
        "The book",
        "The path",
        "The day"
      ],
      "translationStatus": "complete",
      "matchType": "exact",
      "ayahReference": "81:14",
      "occurrenceCount": 1,
      "allOccurrences": [
        {
          "ayahRef": "81:14",
          "position": 1
        }
      ],
      "difficulty": "hard",
      "category": "noun",
      "tags": [
        "noun"
      ]
    },
    {
      "id": "vocab_81_32",
      "arabicWord": "مَّآ",
      "normalizedForm": "ما",
      "transliteration": "Ma",
      "correctMeaning": "What/Not",
      "distractors": [
        "Not",
        "Indeed",
        "When"
      ],
      "translationStatus": "complete",
      "matchType": "exact",
      "ayahReference": "81:14",
      "occurrenceCount": 1,
      "allOccurrences": [
        {
          "ayahRef": "81:14",
          "position": 2
        }
      ],
      "difficulty": "hard",
      "category": "particle",
      "tags": [
        "particle"
      ]
    },
    {
      "id": "vocab_81_33",
      "arabicWord": "أَحۡضَرَتۡ",
      "normalizedForm": "أحضرت",
      "transliteration": "",
      "correctMeaning": "",
      "distractors": [],
      "translationStatus": "pending",
      "matchType": null,
      "ayahReference": "81:14",
      "occurrenceCount": 1,
      "allOccurrences": [
        {
          "ayahRef": "81:14",
          "position": 3
        }
      ],
      "difficulty": "hard",
      "category": "unknown",
      "tags": [
        "needs-review"
      ]
    },
    {
      "id": "vocab_81_34",
      "arabicWord": "فَلَآ",
      "normalizedForm": "فلا",
      "transliteration": "La",
      "correctMeaning": "No/Not",
      "distractors": [
        "Not",
        "Indeed",
        "When"
      ],
      "translationStatus": "complete",
      "matchType": "partial",
      "ayahReference": "81:15",
      "occurrenceCount": 1,
      "allOccurrences": [
        {
          "ayahRef": "81:15",
          "position": 0
        }
      ],
      "difficulty": "hard",
      "category": "particle",
      "tags": [
        "particle"
      ]
    },
    {
      "id": "vocab_81_35",
      "arabicWord": "أُقۡسِمُ",
      "normalizedForm": "أقسم",
      "transliteration": "",
      "correctMeaning": "",
      "distractors": [],
      "translationStatus": "pending",
      "matchType": null,
      "ayahReference": "81:15",
      "occurrenceCount": 1,
      "allOccurrences": [
        {
          "ayahRef": "81:15",
          "position": 1
        }
      ],
      "difficulty": "hard",
      "category": "unknown",
      "tags": [
        "needs-review"
      ]
    },
    {
      "id": "vocab_81_36",
      "arabicWord": "بِٱلۡخُنَّسِ",
      "normalizedForm": "بالخنس",
      "transliteration": "",
      "correctMeaning": "",
      "distractors": [],
      "translationStatus": "pending",
      "matchType": null,
      "ayahReference": "81:15",
      "occurrenceCount": 1,
      "allOccurrences": [
        {
          "ayahRef": "81:15",
          "position": 2
        }
      ],
      "difficulty": "hard",
      "category": "unknown",
      "tags": [
        "needs-review"
      ]
    },
    {
      "id": "vocab_81_37",
      "arabicWord": "ٱلۡجَوَارِ",
      "normalizedForm": "الجوار",
      "transliteration": "",
      "correctMeaning": "",
      "distractors": [],
      "translationStatus": "pending",
      "matchType": null,
      "ayahReference": "81:16",
      "occurrenceCount": 1,
      "allOccurrences": [
        {
          "ayahRef": "81:16",
          "position": 0
        }
      ],
      "difficulty": "hard",
      "category": "unknown",
      "tags": [
        "needs-review"
      ]
    },
    {
      "id": "vocab_81_38",
      "arabicWord": "ٱلۡكُنَّسِ",
      "normalizedForm": "الكنس",
      "transliteration": "Laka",
      "correctMeaning": "For you",
      "distractors": [
        "He",
        "They",
        "We"
      ],
      "translationStatus": "complete",
      "matchType": "partial",
      "ayahReference": "81:16",
      "occurrenceCount": 1,
      "allOccurrences": [
        {
          "ayahRef": "81:16",
          "position": 1
        }
      ],
      "difficulty": "hard",
      "category": "pronoun",
      "tags": [
        "pronoun"
      ]
    },
    {
      "id": "vocab_81_39",
      "arabicWord": "وَٱلَّيۡلِ",
      "normalizedForm": "واليل",
      "transliteration": "Layl",
      "correctMeaning": "Night",
      "distractors": [
        "The book",
        "The path",
        "The day"
      ],
      "translationStatus": "complete",
      "matchType": "partial",
      "ayahReference": "81:17",
      "occurrenceCount": 1,
      "allOccurrences": [
        {
          "ayahRef": "81:17",
          "position": 0
        }
      ],
      "difficulty": "hard",
      "category": "noun",
      "tags": [
        "noun"
      ]
    },
    {
      "id": "vocab_81_40",
      "arabicWord": "عَسۡعَسَ",
      "normalizedForm": "عسعس",
      "transliteration": "",
      "correctMeaning": "",
      "distractors": [],
      "translationStatus": "pending",
      "matchType": null,
      "ayahReference": "81:17",
      "occurrenceCount": 1,
      "allOccurrences": [
        {
          "ayahRef": "81:17",
          "position": 2
        }
      ],
      "difficulty": "hard",
      "category": "unknown",
      "tags": [
        "needs-review"
      ]
    },
    {
      "id": "vocab_81_41",
      "arabicWord": "وَٱلصُّبۡحِ",
      "normalizedForm": "والصبح",
      "transliteration": "",
      "correctMeaning": "",
      "distractors": [],
      "translationStatus": "pending",
      "matchType": null,
      "ayahReference": "81:18",
      "occurrenceCount": 1,
      "allOccurrences": [
        {
          "ayahRef": "81:18",
          "position": 0
        }
      ],
      "difficulty": "hard",
      "category": "unknown",
      "tags": [
        "needs-review"
      ]
    },
    {
      "id": "vocab_81_42",
      "arabicWord": "تَنَفَّسَ",
      "normalizedForm": "تنفس",
      "transliteration": "Nafs",
      "correctMeaning": "Soul/Self",
      "distractors": [
        "The book",
        "The path",
        "The day"
      ],
      "translationStatus": "complete",
      "matchType": "partial",
      "ayahReference": "81:18",
      "occurrenceCount": 1,
      "allOccurrences": [
        {
          "ayahRef": "81:18",
          "position": 2
        }
      ],
      "difficulty": "hard",
      "category": "noun",
      "tags": [
        "noun"
      ]
    },
    {
      "id": "vocab_81_43",
      "arabicWord": "إِنَّهُۥ",
      "normalizedForm": "إنه",
      "transliteration": "Inna",
      "correctMeaning": "Indeed/Verily",
      "distractors": [
        "Not",
        "Indeed",
        "When"
      ],
      "translationStatus": "complete",
      "matchType": "partial",
      "ayahReference": "81:19",
      "occurrenceCount": 1,
      "allOccurrences": [
        {
          "ayahRef": "81:19",
          "position": 0
        }
      ],
      "difficulty": "hard",
      "category": "particle",
      "tags": [
        "particle"
      ]
    },
    {
      "id": "vocab_81_44",
      "arabicWord": "لَقَوۡلُ",
      "normalizedForm": "لقول",
      "transliteration": "",
      "correctMeaning": "",
      "distractors": [],
      "translationStatus": "pending",
      "matchType": null,
      "ayahReference": "81:19",
      "occurrenceCount": 1,
      "allOccurrences": [
        {
          "ayahRef": "81:19",
          "position": 1
        }
      ],
      "difficulty": "hard",
      "category": "unknown",
      "tags": [
        "needs-review"
      ]
    },
    {
      "id": "vocab_81_45",
      "arabicWord": "رَسُولٖ",
      "normalizedForm": "رسول",
      "transliteration": "Rasool",
      "correctMeaning": "Messenger",
      "distractors": [
        "The book",
        "The path",
        "The day"
      ],
      "translationStatus": "complete",
      "matchType": "exact",
      "ayahReference": "81:19",
      "occurrenceCount": 1,
      "allOccurrences": [
        {
          "ayahRef": "81:19",
          "position": 2
        }
      ],
      "difficulty": "hard",
      "category": "noun",
      "tags": [
        "noun"
      ]
    },
    {
      "id": "vocab_81_46",
      "arabicWord": "كَرِيمٖ",
      "normalizedForm": "كريم",
      "transliteration": "Kareem",
      "correctMeaning": "The Generous",
      "distractors": [
        "The Creator",
        "The Provider",
        "The Sustainer"
      ],
      "translationStatus": "complete",
      "matchType": "exact",
      "ayahReference": "81:19",
      "occurrenceCount": 1,
      "allOccurrences": [
        {
          "ayahRef": "81:19",
          "position": 3
        }
      ],
      "difficulty": "hard",
      "category": "name-of-allah",
      "tags": [
        "name-of-allah"
      ]
    },
    {
      "id": "vocab_81_47",
      "arabicWord": "ذِي",
      "normalizedForm": "ذي",
      "transliteration": "",
      "correctMeaning": "",
      "distractors": [],
      "translationStatus": "pending",
      "matchType": null,
      "ayahReference": "81:20",
      "occurrenceCount": 2,
      "allOccurrences": [
        {
          "ayahRef": "81:20",
          "position": 0
        },
        {
          "ayahRef": "81:20",
          "position": 3
        }
      ],
      "difficulty": "hard",
      "category": "unknown",
      "tags": [
        "needs-review"
      ]
    },
    {
      "id": "vocab_81_48",
      "arabicWord": "قُوَّةٍ",
      "normalizedForm": "قوة",
      "transliteration": "",
      "correctMeaning": "",
      "distractors": [],
      "translationStatus": "pending",
      "matchType": null,
      "ayahReference": "81:20",
      "occurrenceCount": 1,
      "allOccurrences": [
        {
          "ayahRef": "81:20",
          "position": 1
        }
      ],
      "difficulty": "hard",
      "category": "unknown",
      "tags": [
        "needs-review"
      ]
    },
    {
      "id": "vocab_81_49",
      "arabicWord": "عِندَ",
      "normalizedForm": "عند",
      "transliteration": "Inda",
      "correctMeaning": "At/With",
      "distractors": [
        "In",
        "From",
        "To"
      ],
      "translationStatus": "complete",
      "matchType": "exact",
      "ayahReference": "81:20",
      "occurrenceCount": 1,
      "allOccurrences": [
        {
          "ayahRef": "81:20",
          "position": 2
        }
      ],
      "difficulty": "hard",
      "category": "preposition",
      "tags": [
        "preposition"
      ]
    },
    {
      "id": "vocab_81_50",
      "arabicWord": "ٱلۡعَرۡشِ",
      "normalizedForm": "العرش",
      "transliteration": "Arsh",
      "correctMeaning": "Throne",
      "distractors": [
        "The book",
        "The path",
        "The day"
      ],
      "translationStatus": "complete",
      "matchType": "root",
      "ayahReference": "81:20",
      "occurrenceCount": 1,
      "allOccurrences": [
        {
          "ayahRef": "81:20",
          "position": 4
        }
      ],
      "difficulty": "hard",
      "category": "noun",
      "tags": [
        "noun"
      ]
    },
    {
      "id": "vocab_81_51",
      "arabicWord": "مَكِينٖ",
      "normalizedForm": "مكين",
      "transliteration": "",
      "correctMeaning": "",
      "distractors": [],
      "translationStatus": "pending",
      "matchType": null,
      "ayahReference": "81:20",
      "occurrenceCount": 1,
      "allOccurrences": [
        {
          "ayahRef": "81:20",
          "position": 5
        }
      ],
      "difficulty": "hard",
      "category": "unknown",
      "tags": [
        "needs-review"
      ]
    },
    {
      "id": "vocab_81_52",
      "arabicWord": "مُّطَاعٖ",
      "normalizedForm": "مطاع",
      "transliteration": "",
      "correctMeaning": "",
      "distractors": [],
      "translationStatus": "pending",
      "matchType": null,
      "ayahReference": "81:21",
      "occurrenceCount": 1,
      "allOccurrences": [
        {
          "ayahRef": "81:21",
          "position": 0
        }
      ],
      "difficulty": "hard",
      "category": "unknown",
      "tags": [
        "needs-review"
      ]
    },
    {
      "id": "vocab_81_53",
      "arabicWord": "ثَمَّ",
      "normalizedForm": "ثم",
      "transliteration": "Thumma",
      "correctMeaning": "Then",
      "distractors": [
        "Not",
        "Indeed",
        "When"
      ],
      "translationStatus": "complete",
      "matchType": "exact",
      "ayahReference": "81:21",
      "occurrenceCount": 1,
      "allOccurrences": [
        {
          "ayahRef": "81:21",
          "position": 1
        }
      ],
      "difficulty": "hard",
      "category": "particle",
      "tags": [
        "particle"
      ]
    },
    {
      "id": "vocab_81_54",
      "arabicWord": "أَمِينٖ",
      "normalizedForm": "أمين",
      "transliteration": "",
      "correctMeaning": "",
      "distractors": [],
      "translationStatus": "pending",
      "matchType": null,
      "ayahReference": "81:21",
      "occurrenceCount": 1,
      "allOccurrences": [
        {
          "ayahRef": "81:21",
          "position": 2
        }
      ],
      "difficulty": "hard",
      "category": "unknown",
      "tags": [
        "needs-review"
      ]
    },
    {
      "id": "vocab_81_55",
      "arabicWord": "وَمَا",
      "normalizedForm": "وما",
      "transliteration": "Ma",
      "correctMeaning": "What/Not",
      "distractors": [
        "Not",
        "Indeed",
        "When"
      ],
      "translationStatus": "complete",
      "matchType": "root",
      "ayahReference": "81:22",
      "occurrenceCount": 4,
      "allOccurrences": [
        {
          "ayahRef": "81:22",
          "position": 0
        },
        {
          "ayahRef": "81:24",
          "position": 0
        },
        {
          "ayahRef": "81:25",
          "position": 0
        },
        {
          "ayahRef": "81:29",
          "position": 0
        }
      ],
      "difficulty": "medium",
      "category": "particle",
      "tags": [
        "particle"
      ]
    },
    {
      "id": "vocab_81_56",
      "arabicWord": "صَاحِبُكُم",
      "normalizedForm": "صاحبكم",
      "transliteration": "Habba",
      "correctMeaning": "He loved",
      "distractors": [
        "He went",
        "They came",
        "We saw"
      ],
      "translationStatus": "complete",
      "matchType": "partial",
      "ayahReference": "81:22",
      "occurrenceCount": 1,
      "allOccurrences": [
        {
          "ayahRef": "81:22",
          "position": 1
        }
      ],
      "difficulty": "hard",
      "category": "verb",
      "tags": [
        "verb"
      ]
    },
    {
      "id": "vocab_81_57",
      "arabicWord": "بِمَجۡنُونٖ",
      "normalizedForm": "بمجنون",
      "transliteration": "Jinn",
      "correctMeaning": "Jinn",
      "distractors": [
        "The book",
        "The path",
        "The day"
      ],
      "translationStatus": "complete",
      "matchType": "partial",
      "ayahReference": "81:22",
      "occurrenceCount": 1,
      "allOccurrences": [
        {
          "ayahRef": "81:22",
          "position": 2
        }
      ],
      "difficulty": "hard",
      "category": "noun",
      "tags": [
        "noun"
      ]
    },
    {
      "id": "vocab_81_58",
      "arabicWord": "وَلَقَدۡ",
      "normalizedForm": "ولقد",
      "transliteration": "Qad",
      "correctMeaning": "Already/Indeed",
      "distractors": [
        "Not",
        "Indeed",
        "When"
      ],
      "translationStatus": "complete",
      "matchType": "root",
      "ayahReference": "81:23",
      "occurrenceCount": 1,
      "allOccurrences": [
        {
          "ayahRef": "81:23",
          "position": 0
        }
      ],
      "difficulty": "hard",
      "category": "particle",
      "tags": [
        "particle"
      ]
    },
    {
      "id": "vocab_81_59",
      "arabicWord": "رَءَاهُ",
      "normalizedForm": "رءاه",
      "transliteration": "",
      "correctMeaning": "",
      "distractors": [],
      "translationStatus": "pending",
      "matchType": null,
      "ayahReference": "81:23",
      "occurrenceCount": 1,
      "allOccurrences": [
        {
          "ayahRef": "81:23",
          "position": 1
        }
      ],
      "difficulty": "hard",
      "category": "unknown",
      "tags": [
        "needs-review"
      ]
    },
    {
      "id": "vocab_81_60",
      "arabicWord": "بِٱلۡأُفُقِ",
      "normalizedForm": "بالأفق",
      "transliteration": "",
      "correctMeaning": "",
      "distractors": [],
      "translationStatus": "pending",
      "matchType": null,
      "ayahReference": "81:23",
      "occurrenceCount": 1,
      "allOccurrences": [
        {
          "ayahRef": "81:23",
          "position": 2
        }
      ],
      "difficulty": "hard",
      "category": "unknown",
      "tags": [
        "needs-review"
      ]
    },
    {
      "id": "vocab_81_61",
      "arabicWord": "ٱلۡمُبِينِ",
      "normalizedForm": "المبين",
      "transliteration": "Lam",
      "correctMeaning": "Did not",
      "distractors": [
        "Not",
        "Indeed",
        "When"
      ],
      "translationStatus": "complete",
      "matchType": "partial",
      "ayahReference": "81:23",
      "occurrenceCount": 1,
      "allOccurrences": [
        {
          "ayahRef": "81:23",
          "position": 3
        }
      ],
      "difficulty": "hard",
      "category": "particle",
      "tags": [
        "particle"
      ]
    },
    {
      "id": "vocab_81_62",
      "arabicWord": "هُوَ",
      "normalizedForm": "هو",
      "transliteration": "Huwa",
      "correctMeaning": "He",
      "distractors": [
        "He",
        "They",
        "We"
      ],
      "translationStatus": "complete",
      "matchType": "exact",
      "ayahReference": "81:24",
      "occurrenceCount": 3,
      "allOccurrences": [
        {
          "ayahRef": "81:24",
          "position": 1
        },
        {
          "ayahRef": "81:25",
          "position": 1
        },
        {
          "ayahRef": "81:27",
          "position": 1
        }
      ],
      "difficulty": "medium",
      "category": "pronoun",
      "tags": [
        "pronoun"
      ]
    },
    {
      "id": "vocab_81_63",
      "arabicWord": "عَلَى",
      "normalizedForm": "على",
      "transliteration": "Ala",
      "correctMeaning": "Upon/On",
      "distractors": [
        "In",
        "From",
        "To"
      ],
      "translationStatus": "complete",
      "matchType": "exact",
      "ayahReference": "81:24",
      "occurrenceCount": 1,
      "allOccurrences": [
        {
          "ayahRef": "81:24",
          "position": 2
        }
      ],
      "difficulty": "hard",
      "category": "preposition",
      "tags": [
        "preposition"
      ]
    },
    {
      "id": "vocab_81_64",
      "arabicWord": "ٱلۡغَيۡبِ",
      "normalizedForm": "الغيب",
      "transliteration": "",
      "correctMeaning": "",
      "distractors": [],
      "translationStatus": "pending",
      "matchType": null,
      "ayahReference": "81:24",
      "occurrenceCount": 1,
      "allOccurrences": [
        {
          "ayahRef": "81:24",
          "position": 3
        }
      ],
      "difficulty": "hard",
      "category": "unknown",
      "tags": [
        "needs-review"
      ]
    },
    {
      "id": "vocab_81_65",
      "arabicWord": "بِضَنِينٖ",
      "normalizedForm": "بضنين",
      "transliteration": "",
      "correctMeaning": "",
      "distractors": [],
      "translationStatus": "pending",
      "matchType": null,
      "ayahReference": "81:24",
      "occurrenceCount": 1,
      "allOccurrences": [
        {
          "ayahRef": "81:24",
          "position": 4
        }
      ],
      "difficulty": "hard",
      "category": "unknown",
      "tags": [
        "needs-review"
      ]
    },
    {
      "id": "vocab_81_66",
      "arabicWord": "بِقَوۡلِ",
      "normalizedForm": "بقول",
      "transliteration": "",
      "correctMeaning": "",
      "distractors": [],
      "translationStatus": "pending",
      "matchType": null,
      "ayahReference": "81:25",
      "occurrenceCount": 1,
      "allOccurrences": [
        {
          "ayahRef": "81:25",
          "position": 2
        }
      ],
      "difficulty": "hard",
      "category": "unknown",
      "tags": [
        "needs-review"
      ]
    },
    {
      "id": "vocab_81_67",
      "arabicWord": "شَيۡطَٰنٖ",
      "normalizedForm": "شيطٰن",
      "transliteration": "",
      "correctMeaning": "",
      "distractors": [],
      "translationStatus": "pending",
      "matchType": null,
      "ayahReference": "81:25",
      "occurrenceCount": 1,
      "allOccurrences": [
        {
          "ayahRef": "81:25",
          "position": 3
        }
      ],
      "difficulty": "hard",
      "category": "unknown",
      "tags": [
        "needs-review"
      ]
    },
    {
      "id": "vocab_81_68",
      "arabicWord": "رَّجِيمٖ",
      "normalizedForm": "رجيم",
      "transliteration": "",
      "correctMeaning": "",
      "distractors": [],
      "translationStatus": "pending",
      "matchType": null,
      "ayahReference": "81:25",
      "occurrenceCount": 1,
      "allOccurrences": [
        {
          "ayahRef": "81:25",
          "position": 4
        }
      ],
      "difficulty": "hard",
      "category": "unknown",
      "tags": [
        "needs-review"
      ]
    },
    {
      "id": "vocab_81_69",
      "arabicWord": "فَأَيۡنَ",
      "normalizedForm": "فأين",
      "transliteration": "",
      "correctMeaning": "",
      "distractors": [],
      "translationStatus": "pending",
      "matchType": null,
      "ayahReference": "81:26",
      "occurrenceCount": 1,
      "allOccurrences": [
        {
          "ayahRef": "81:26",
          "position": 0
        }
      ],
      "difficulty": "hard",
      "category": "unknown",
      "tags": [
        "needs-review"
      ]
    },
    {
      "id": "vocab_81_70",
      "arabicWord": "تَذۡهَبُونَ",
      "normalizedForm": "تذهبون",
      "transliteration": "Dhahaba",
      "correctMeaning": "He went",
      "distractors": [
        "He went",
        "They came",
        "We saw"
      ],
      "translationStatus": "complete",
      "matchType": "partial",
      "ayahReference": "81:26",
      "occurrenceCount": 1,
      "allOccurrences": [
        {
          "ayahRef": "81:26",
          "position": 1
        }
      ],
      "difficulty": "hard",
      "category": "verb",
      "tags": [
        "verb"
      ]
    },
    {
      "id": "vocab_81_71",
      "arabicWord": "إِنۡ",
      "normalizedForm": "إن",
      "transliteration": "Inna",
      "correctMeaning": "Indeed/Verily",
      "distractors": [
        "Not",
        "Indeed",
        "When"
      ],
      "translationStatus": "complete",
      "matchType": "exact",
      "ayahReference": "81:27",
      "occurrenceCount": 1,
      "allOccurrences": [
        {
          "ayahRef": "81:27",
          "position": 0
        }
      ],
      "difficulty": "hard",
      "category": "particle",
      "tags": [
        "particle"
      ]
    },
    {
      "id": "vocab_81_72",
      "arabicWord": "إِلَّا",
      "normalizedForm": "إلا",
      "transliteration": "La",
      "correctMeaning": "No/Not",
      "distractors": [
        "Not",
        "Indeed",
        "When"
      ],
      "translationStatus": "complete",
      "matchType": "partial",
      "ayahReference": "81:27",
      "occurrenceCount": 2,
      "allOccurrences": [
        {
          "ayahRef": "81:27",
          "position": 2
        },
        {
          "ayahRef": "81:29",
          "position": 2
        }
      ],
      "difficulty": "hard",
      "category": "particle",
      "tags": [
        "particle"
      ]
    },
    {
      "id": "vocab_81_73",
      "arabicWord": "ذِكۡرٞ",
      "normalizedForm": "ذكر",
      "transliteration": "Dhikr",
      "correctMeaning": "Remembrance",
      "distractors": [
        "The book",
        "The path",
        "The day"
      ],
      "translationStatus": "complete",
      "matchType": "exact",
      "ayahReference": "81:27",
      "occurrenceCount": 1,
      "allOccurrences": [
        {
          "ayahRef": "81:27",
          "position": 3
        }
      ],
      "difficulty": "hard",
      "category": "noun",
      "tags": [
        "noun"
      ]
    },
    {
      "id": "vocab_81_74",
      "arabicWord": "لِّلۡعَٰلَمِينَ",
      "normalizedForm": "للعٰلمين",
      "transliteration": "Lam",
      "correctMeaning": "Did not",
      "distractors": [
        "Not",
        "Indeed",
        "When"
      ],
      "translationStatus": "complete",
      "matchType": "partial",
      "ayahReference": "81:27",
      "occurrenceCount": 1,
      "allOccurrences": [
        {
          "ayahRef": "81:27",
          "position": 4
        }
      ],
      "difficulty": "hard",
      "category": "particle",
      "tags": [
        "particle"
      ]
    },
    {
      "id": "vocab_81_75",
      "arabicWord": "لِمَن",
      "normalizedForm": "لمن",
      "transliteration": "Min",
      "correctMeaning": "From/Of",
      "distractors": [
        "In",
        "From",
        "To"
      ],
      "translationStatus": "complete",
      "matchType": "root",
      "ayahReference": "81:28",
      "occurrenceCount": 1,
      "allOccurrences": [
        {
          "ayahRef": "81:28",
          "position": 0
        }
      ],
      "difficulty": "hard",
      "category": "preposition",
      "tags": [
        "preposition"
      ]
    },
    {
      "id": "vocab_81_76",
      "arabicWord": "شَآءَ",
      "normalizedForm": "شاء",
      "transliteration": "Sha'a",
      "correctMeaning": "He willed",
      "distractors": [
        "He went",
        "They came",
        "We saw"
      ],
      "translationStatus": "complete",
      "matchType": "exact",
      "ayahReference": "81:28",
      "occurrenceCount": 1,
      "allOccurrences": [
        {
          "ayahRef": "81:28",
          "position": 1
        }
      ],
      "difficulty": "hard",
      "category": "verb",
      "tags": [
        "verb"
      ]
    },
    {
      "id": "vocab_81_77",
      "arabicWord": "مِنكُمۡ",
      "normalizedForm": "منكم",
      "transliteration": "Minkum",
      "correctMeaning": "From you",
      "distractors": [
        "He",
        "They",
        "We"
      ],
      "translationStatus": "complete",
      "matchType": "exact",
      "ayahReference": "81:28",
      "occurrenceCount": 1,
      "allOccurrences": [
        {
          "ayahRef": "81:28",
          "position": 2
        }
      ],
      "difficulty": "hard",
      "category": "pronoun",
      "tags": [
        "pronoun"
      ]
    },
    {
      "id": "vocab_81_78",
      "arabicWord": "أَن",
      "normalizedForm": "أن",
      "transliteration": "",
      "correctMeaning": "",
      "distractors": [],
      "translationStatus": "pending",
      "matchType": null,
      "ayahReference": "81:28",
      "occurrenceCount": 2,
      "allOccurrences": [
        {
          "ayahRef": "81:28",
          "position": 3
        },
        {
          "ayahRef": "81:29",
          "position": 3
        }
      ],
      "difficulty": "hard",
      "category": "unknown",
      "tags": [
        "needs-review"
      ]
    },
    {
      "id": "vocab_81_79",
      "arabicWord": "يَسۡتَقِيمَ",
      "normalizedForm": "يستقيم",
      "transliteration": "",
      "correctMeaning": "",
      "distractors": [],
      "translationStatus": "pending",
      "matchType": null,
      "ayahReference": "81:28",
      "occurrenceCount": 1,
      "allOccurrences": [
        {
          "ayahRef": "81:28",
          "position": 4
        }
      ],
      "difficulty": "hard",
      "category": "unknown",
      "tags": [
        "needs-review"
      ]
    },
    {
      "id": "vocab_81_80",
      "arabicWord": "تَشَآءُونَ",
      "normalizedForm": "تشاءون",
      "transliteration": "Sha'a",
      "correctMeaning": "He willed",
      "distractors": [
        "He went",
        "They came",
        "We saw"
      ],
      "translationStatus": "complete",
      "matchType": "partial",
      "ayahReference": "81:29",
      "occurrenceCount": 1,
      "allOccurrences": [
        {
          "ayahRef": "81:29",
          "position": 1
        }
      ],
      "difficulty": "hard",
      "category": "verb",
      "tags": [
        "verb"
      ]
    },
    {
      "id": "vocab_81_81",
      "arabicWord": "يَشَآءَ",
      "normalizedForm": "يشاء",
      "transliteration": "Sha'a",
      "correctMeaning": "He willed",
      "distractors": [
        "He went",
        "They came",
        "We saw"
      ],
      "translationStatus": "complete",
      "matchType": "partial",
      "ayahReference": "81:29",
      "occurrenceCount": 1,
      "allOccurrences": [
        {
          "ayahRef": "81:29",
          "position": 4
        }
      ],
      "difficulty": "hard",
      "category": "verb",
      "tags": [
        "verb"
      ]
    },
    {
      "id": "vocab_81_82",
      "arabicWord": "ٱللَّهُ",
      "normalizedForm": "الله",
      "transliteration": "Allah",
      "correctMeaning": "Allah (God)",
      "distractors": [
        "The Creator",
        "The Provider",
        "The Sustainer"
      ],
      "translationStatus": "complete",
      "matchType": "exact",
      "ayahReference": "81:29",
      "occurrenceCount": 1,
      "allOccurrences": [
        {
          "ayahRef": "81:29",
          "position": 5
        }
      ],
      "difficulty": "hard",
      "category": "name-of-allah",
      "tags": [
        "name-of-allah"
      ]
    },
    {
      "id": "vocab_81_83",
      "arabicWord": "رَبُّ",
      "normalizedForm": "رب",
      "transliteration": "Rabb",
      "correctMeaning": "Lord",
      "distractors": [
        "The Creator",
        "The Provider",
        "The Sustainer"
      ],
      "translationStatus": "complete",
      "matchType": "exact",
      "ayahReference": "81:29",
      "occurrenceCount": 1,
      "allOccurrences": [
        {
          "ayahRef": "81:29",
          "position": 6
        }
      ],
      "difficulty": "hard",
      "category": "name-of-allah",
      "tags": [
        "name-of-allah"
      ]
    },
    {
      "id": "vocab_81_84",
      "arabicWord": "ٱلۡعَٰلَمِينَ",
      "normalizedForm": "العٰلمين",
      "transliteration": "Lam",
      "correctMeaning": "Did not",
      "distractors": [
        "Not",
        "Indeed",
        "When"
      ],
      "translationStatus": "complete",
      "matchType": "partial",
      "ayahReference": "81:29",
      "occurrenceCount": 1,
      "allOccurrences": [
        {
          "ayahRef": "81:29",
          "position": 7
        }
      ],
      "difficulty": "hard",
      "category": "particle",
      "tags": [
        "particle"
      ]
    }
  ],
  "tafsirQuiz": [
    {
      "id": "tafsir_81_1_0",
      "type": "tafsir",
      "questionType": "warningPromise",
      "question": "What does this verse warn or promise?",
      "correctAnswer": "The scenes of Doomsday, or the Day of Judgement, have been described at various points in the Quran. When Doomsday arrives, the present balance of the world will break down, and man will feel himself helpless",
      "distractors": [
        "This verse explains the rules of inheritance",
        "This verse describes the characteristics of believers",
        "This verse talks about the stories of previous prophets"
      ],
      "surahNumber": 81,
      "ayahNumber": 1,
      "ayahKey": "81:1",
      "themes": {
        "hasWarning": true,
        "hasPromise": false,
        "hasGuidance": false,
        "hasWorship": false,
        "hasUnity": false,
        "hasMorality": false,
        "hasHereafter": true,
        "hasCreation": true
      },
      "difficulty": "easy",
      "keywords": [
        "doom",
        "day of judgement",
        "world"
      ],
      "coveredAyahs": [
        "81:1",
        "81:2",
        "81:3",
        "81:4",
        "81:5",
        "81:6",
        "81:7",
        "81:8",
        "81:9",
        "81:10",
        "81:11",
        "81:12",
        "81:13",
        "81:14"
      ]
    },
    {
      "id": "tafsir_81_15_1",
      "type": "tafsir",
      "questionType": "concept",
      "question": "What key concept does this verse highlight?",
      "correctAnswer": "The controlled movement of the earth symbolically helps us in understanding the miraculous nature of man’s contact with God through the angel. The axial rotation of the earth is one of the truly remarkable phenomena of this universe",
      "distractors": [
        "This verse narrates a historical event",
        "This verse gives rulings on trade and commerce",
        "This verse promises paradise to the righteous"
      ],
      "surahNumber": 81,
      "ayahNumber": 15,
      "ayahKey": "81:15",
      "themes": {
        "hasWarning": false,
        "hasPromise": false,
        "hasGuidance": true,
        "hasWorship": false,
        "hasUnity": false,
        "hasMorality": false,
        "hasHereafter": false,
        "hasCreation": true
      },
      "difficulty": "medium",
      "keywords": [
        "understand",
        "earth",
        "universe",
        "nature"
      ],
      "coveredAyahs": [
        "81:15",
        "81:16",
        "81:17",
        "81:18"
      ]
    },
    {
      "id": "tafsir_81_20_2",
      "type": "tafsir",
      "questionType": "warningPromise",
      "question": "What consequence is described in this ayah?",
      "correctAnswer": "The Quran informs us that the Day of Judgement will finally come: all of humanity will be assembled on that Day and will be rewarded or punished according to their deeds",
      "distractors": [
        "This verse discusses the creation of the universe",
        "This verse talks about the stories of previous prophets",
        "This verse explains the rules of inheritance"
      ],
      "surahNumber": 81,
      "ayahNumber": 20,
      "ayahKey": "81:20",
      "themes": {
        "hasWarning": false,
        "hasPromise": true,
        "hasGuidance": true,
        "hasWorship": false,
        "hasUnity": false,
        "hasMorality": true,
        "hasHereafter": true,
        "hasCreation": true
      },
      "difficulty": "medium",
      "keywords": [
        "reward",
        "light",
        "understand",
        "just",
        "day of judgement"
      ],
      "coveredAyahs": [
        "81:20",
        "81:21",
        "81:22",
        "81:23",
        "81:24",
        "81:25",
        "81:26",
        "81:27",
        "81:28",
        "81:29",
        "82:1",
        "82:2",
        "82:3",
        "82:4",
        "82:5",
        "82:6",
        "82:7",
        "82:8",
        "82:9",
        "82:10",
        "82:11",
        "82:12"
      ]
    }
  ],
  "metadata": {
    "totalVocabQuestions": 84,
    "totalTafsirQuestions": 0,
    "totalAyahs": 29,
    "translationStats": {
      "complete": 46,
      "pending": 38,
      "completionRate": 55
    },
    "difficultyBreakdown": {
      "easy": 1,
      "medium": 3,
      "hard": 80
    }
  },
  "tafsirQuizCount": 3
}